i3_dstatus-0.1.1.data/scripts/i3-dstatus
i3dstatus/__init__.py
i3dstatus/__main__.py
i3dstatus/block.py
i3dstatus/service.py
i3dstatus/generators/battery
i3dstatus/generators/check-http
i3dstatus/generators/clipboard
i3dstatus/generators/clock
i3dstatus/generators/disk
i3dstatus/generators/focused-window
i3dstatus/generators/github-repos
i3dstatus/generators/netifaces
i3dstatus/generators/playerctl
i3dstatus/generators/scratchpad
i3_dstatus-0.1.1.dist-info/LICENSE
i3_dstatus-0.1.1.dist-info/METADATA
i3_dstatus-0.1.1.dist-info/WHEEL
i3_dstatus-0.1.1.dist-info/entry_points.txt
i3_dstatus-0.1.1.dist-info/top_level.txt
i3_dstatus-0.1.1.dist-info/RECORD
