Metadata-Version: 2.1
Name: i3-dstatus
Version: 0.1.1
Summary: The ultimate DIY statusline generator for i3
Home-page: https://github.com/altdesktop/i3-dstatus
Author: Tony Crisci
Author-email: tony@dubstepdish.com
License: BSD
Platform: UNKNOWN
Classifier: Development Status :: 4 - Beta
Classifier: License :: OSI Approved :: BSD License
Classifier: Programming Language :: Python :: 3
Requires-Dist: PyYAML
Requires-Dist: netifaces
Requires-Dist: i3ipc
Requires-Dist: requests
Requires-Dist: dbus-next
